{
  "full_name": "Le Minh Khoi",
  "years_of_experience": 9.0,
  "technical_skills": [
    "Giai tich",
    "Dai so tuyen tinh",
    "Xac suat thong ke",
    "Toan ung dung",
    "Matlab",
    "LaTeX"
  ],
  "soft_skills": [
    "Tu duy logic",
    "Truyen dat",
    "Huong dan sinh vien",
    "Quan ly hoc phan"
  ],
  "education": "Thac si Toan giai tich, Dai hoc Khoa hoc Tu nhien TP.HCM, 2012",
  "summary": "Le Minh Khoi has 9 years of experience as a senior mathematics lecturer, specializing in advanced analysis, statistics, and applied mathematics. He excels at integrating theoretical concepts with real-world applications and prefers interactive, logic-based teaching methods. His strong analytical and mentoring skills make him a valuable asset for academic and research environments."
}