{
  "full_name": "Vo Anh Thu",
  "years_of_experience": 4.0,
  "technical_skills": [
    "Toán cao cấp",
    "Xác suất thống kê",
    "Tối ưu hóa",
    "Excel",
    "Python cơ bản",
    "LaTeX"
  ],
  "soft_skills": [
    "Giao tiếp sâu phạm",
    "Tổ chức học liệu",
    "Làm việc nhóm",
    "Chủ động"
  ],
  "education": "Thạc sĩ Toán ứng dụng, Đại học Kinh tế TP.HCM, 2021",
  "summary": "Ứng viên có kinh nghiệm giảng dạy Toán đại cương và Toán kinh tế, xây dựng tài liệu học tập và bài tập đánh giá. Đã giảng dạy Toán cao cấp và xác suất thống kê cho sinh viên năm nhất. Mong muốn đóng góp vào đào tạo Toán theo hướng ứng dụng."
}